nexus3d/__init__.py
nexus3d/coordinate_systems.py
nexus3d/matrix.py
nexus3d/nexus_transformations.py
nexus3d/units.py
nexus3d/formats/__init__.py
nexus3d/formats/gltf_writer.py
nexus3d/formats/interfaces.py
nexus3d/formats/mesh.py
nexus3d/formats/stl_writer.py
nexus3d-0.0.7.dist-info/LICENSE
nexus3d-0.0.7.dist-info/METADATA
nexus3d-0.0.7.dist-info/WHEEL
nexus3d-0.0.7.dist-info/entry_points.txt
nexus3d-0.0.7.dist-info/top_level.txt
nexus3d-0.0.7.dist-info/RECORD
