Metadata-Version: 2.1
Name: nexus3d
Version: 0.0.7
Summary: Convert NXtransformation matrices inside a nexus file to 3D file formats
Author-email: Florian Dobener <florian.dobener@physik.hu-berlin.de>
License: Apache License
Project-URL: homepage, https://github.com/domna/nexus3d
Project-URL: repository, https://github.com/domna/nexus3d
Project-URL: tracker, https://github.com/domna/nexus3d/issues
Project-URL: download, https://github.com/domna/nexus3d/releases
Classifier: Programming Language :: Python :: 3.8
Classifier: Programming Language :: Python :: 3.9
Classifier: Programming Language :: Python :: 3.10
Classifier: Programming Language :: Python :: 3.11
Classifier: Programming Language :: Python :: 3.12
Classifier: License :: OSI Approved :: Apache Software License
Classifier: Operating System :: OS Independent
Requires-Python: >=3.8
License-File: LICENSE
Requires-Dist: h5py >=3.8.0
Requires-Dist: numpy
Requires-Dist: pint
Requires-Dist: numpy-stl
Requires-Dist: click
Requires-Dist: pygltflib
Requires-Dist: xarray
Provides-Extra: dev
Requires-Dist: mypy ; extra == 'dev'
Requires-Dist: ruff ==0.4.10 ; extra == 'dev'
Requires-Dist: pycodestyle ; extra == 'dev'
Requires-Dist: pytest ; extra == 'dev'
Requires-Dist: pytest-cov ; extra == 'dev'
Requires-Dist: scipy ; extra == 'dev'
